examples/container_type_preservation.py
examples/new_config_features.py
examples/pydantic_computed_fields.py
examples/pydantic_computed_fields_transfer.py
examples/pydantic_config_semantics.py
examples/pydantic_interop.py
examples/pydantic_validators.py
examples/type_cache_usage.py
modict/__init__.py
modict/_modict.py
modict/_modict_meta.py
modict/_pydantic_interop.py
modict/_collections_utils/__init__.py
modict/_collections_utils/_advanced.py
modict/_collections_utils/_basic.py
modict/_collections_utils/_missing.py
modict/_collections_utils/_path.py
modict/_collections_utils/_types.py
modict/_collections_utils/_view.py
modict/_typechecker/__init__.py
modict/_typechecker/_coercer.py
modict/_typechecker/_public_api.py
modict/_typechecker/_typechecker.py
modict-0.3.3.dist-info/licenses/LICENSE
tests/__init__.py
tests/run_tests.py
tests/test_advanced.py
tests/test_alias_generator.py
tests/test_basic_utils.py
tests/test_check_keys.py
tests/test_class_schema.py
tests/test_config_allow_inf_nan.py
tests/test_config_features.py
tests/test_container_type_preservation.py
tests/test_deep_operations.py
tests/test_field_constraints.py
tests/test_field_factory.py
tests/test_field_factory_signature.py
tests/test_from_attributes.py
tests/test_get_set_key.py
tests/test_jsonpath.py
tests/test_modict.py
tests/test_modict_meta.py
tests/test_package_meta.py
tests/test_path_normalize.py
tests/test_populate_by_name_alias.py
tests/test_public_api_exports.py
tests/test_pydantic_computed_transfer.py
tests/test_pydantic_config_interop.py
tests/test_pydantic_interop.py
tests/test_serialization_options.py
tests/test_set_key_params.py
tests/test_type_cache.py
tests/test_typechecker.py
tests/test_use_enum_values.py
tests/test_validate_default.py
tests/test_view.py
tests/__pycache__/__init__.cpython-312.pyc
tests/__pycache__/__init__.cpython-314.pyc
tests/__pycache__/test_advanced.cpython-312-pytest-9.0.2.pyc
tests/__pycache__/test_advanced.cpython-314-pytest-9.0.2.pyc
tests/__pycache__/test_alias_generator.cpython-312-pytest-9.0.2.pyc
modict-0.3.3.dist-info/METADATA
modict-0.3.3.dist-info/WHEEL
modict-0.3.3.dist-info/top_level.txt
modict-0.3.3.dist-info/RECORD
