Metadata-Version: 2.4
Name: modict
Version: 0.3.3
Summary: A Python package named modict
Author-email: baptiste <bferrand.maths@gmail.com>
License: MIT License
Project-URL: Homepage, https://github.com/B4PT0R/modict
Classifier: Programming Language :: Python :: 3
Classifier: License :: OSI Approved :: MIT License
Classifier: Operating System :: OS Independent
Requires-Python: >=3.10
License-File: LICENSE
Requires-Dist: jsonpath-ng>=1.6.1
Provides-Extra: dev
Requires-Dist: pytest; extra == "dev"
Requires-Dist: pytest-cov; extra == "dev"
Requires-Dist: pytest-html>=4.1.1; extra == "dev"
Requires-Dist: flake8; extra == "dev"
Requires-Dist: black; extra == "dev"
Dynamic: license-file
